LICENSE
README.md
setup.py
aiodiskdb/__init__.py
aiodiskdb/abstracts.py
aiodiskdb/aiodiskdb.py
aiodiskdb/exceptions.py
aiodiskdb/internals.py
aiodiskdb/local_types.py
aiodiskdb/transaction.py
aiodiskdb.egg-info/PKG-INFO
aiodiskdb.egg-info/SOURCES.txt
aiodiskdb.egg-info/dependency_links.txt
aiodiskdb.egg-info/top_level.txt
test/test_checkpoints.py
test/test_concurrency.py
test/test_concurrency_small_files.py
test/test_drop_index.py
test/test_errors.py
test/test_events.py
test/test_ltrim.py
test/test_read_write.py
test/test_rtrim.py
test/test_signals.py
test/test_transaction.py